minner/VERSION
minner/__init__.py
minner/cmdline.py
minner/exceptions.py
minner/commands/__init__.py
minner/commands/boom.py
minner/commands/md5.py
minner/commands/time.py
Minner-0.1.4.dist-info/METADATA
Minner-0.1.4.dist-info/WHEEL
Minner-0.1.4.dist-info/entry_points.txt
Minner-0.1.4.dist-info/top_level.txt
Minner-0.1.4.dist-info/RECORD
